[{"type": "得场鲸", "name": "ブsもM\", "caseSkill": "", "defense": ["32", "2", "0", "0", "0", "0"], "material": {"Fbホ": "2", "}借をブ": "1"}, "skill": {"^_t": "1"}, "decoration": {"0": 0, "1": 0, "2": 0}}, {"type": "得场鲸", "name": "ブsもM]", "caseSkill": "", "defense": ["32", "2", "0", "0", "0", "0"], "material": {"Fbホ": "2", "}借をブ": "1"}, "skill": {}, "decoration": {"0": 1, "1": 0, "2": 0}}, {"type": "得场鲸", "name": "玛ヒもM\", "caseSkill": "", "defense": ["32", "0", "2", "0", "0", "0"], "material": {"Fbホ": "2"}, "skill": {"^_t": "1"}, "decoration": {"0": 0, "1": 0, "2": 0}}, {"type": "得场鲸", "name": "玛ヒもM]", "caseSkill": "", "defense": ["32", "0", "2", "0", "0", "0"], "material": {"Fbホ": "2"}, "skill": {}, "decoration": {"0": 1, "1": 0, "2": 0}}, {"type": "得场鲸", "name": "yH得ヒ\", "caseSkill": "", "defense": ["36", "2", "2", "0", "0", "0"], "material": {"た[s氦Wブ": "2", "た[s氦W澎": "4"}, "skill": {"肩ヱ": "2"}, "decoration": {"0": 0, "1": 0, "2": 0}}, {"type": "得场鲸", "name": "yH得ヒ]", "caseSkill": "", "defense": ["36", "2", "2", "0", "0", "0"], "material": {"た[s氦Wブ": "2", "た[s氦W澎": "4"}, "skill": {"肩ヱ": "1"}, "decoration": {"0": 1, "1": 0, "2": 0}}, {"type": "得场鲸", "name": "癌s得ヒ\", "caseSkill": "", "defense": ["36", "2", "0", "2", "0", "2"], "material": {"}借w癌": "3", "Ws癌": "2"}, "skill": {"KON": "1"}, "decoration": {"0": 0, "1": 0, "2": 0}}, {"type": "得场鲸", "name": "癌s得ヒ]", "caseSkill": "", "defense": ["36", "2", "0", "2", "0", "2"], "material": {"}借w癌": "3", "Ws癌": "2"}, "skill": {"KON": "1"}, "decoration": {"0": 1, "1": 0, "2": 0}}, {"type": "得场鲸", "name": "X鞯氓遥\", "caseSkill": "", "defense": ["36", "-2", "0", "-2", "-2", "0"], "material": {"Fbホ": "2", "谨sホ": "4", "P扯ホ": "5"}, "skill": {"究m": "1"}, "decoration": {"0": 0, "1": 0, "2": 0}}, {"type": "得场鲸", "name": "X鞯氓遥]", "caseSkill": "", "defense": ["36", "-2", "0", "-2", "-2", "0"], "material": {"Fbホ": "2", "谨sホ": "4", "P扯ホ": "5"}, "skill": {"究m": "1"}, "decoration": {"0": 1, "1": 0, "2": 0}}, {"type": "得场鲸", "name": "WàP@S\", "caseSkill": "", "defense": ["42", "-1", "-1", "2", "0", "2"], "material": {"jà获胶": "1", "s叩泊": "2"}, "skill": {"从ネ厩": "2", "辅DJ": "1"}, "decoration": {"0": 1, "1": 0, "2": 0}}, {"type": "得场鲸", "name": "WàP@S]", "caseSkill": "", "defense": ["42", "-1", "-1", "2", "0", "2"], "material": {"jà获胶": "1", "s叩泊": "2"}, "skill": {"从ネ厩": "2"}, "decoration": {"0": 1, "1": 1, "2": 0}}, {"type": "得场鲸", "name": "エ噶得ヒ\", "caseSkill": "", "defense": ["38", "-2", "1", "1", "1", "2"], "material": {"エ噶喊泶": "4", "エ噶毫ˇ": "2", "]@G": "3"}, "skill": {"陈肤妮┦jて": "2"}, "decoration": {"0": 0, "1": 0, "2": 0}}, {"type": "得场鲸", "name": "エ噶得ヒ]", "caseSkill": "", "defense": ["38", "-2", "1", "1", "1", "2"], "material": {"エ噶喊泶": "4", "エ噶毫ˇ": "2", "]@G": "3"}, "skill": {"陈肤妮┦jて": "1"}, "decoration": {"0": 1, "1": 0, "2": 0}}, {"type": "得场鲸", "name": "エヒ挛得ヒ\", "caseSkill": "", "defense": ["38", "-1", "-1", "0", "0", "2"], "material": {"エヒ挛喊泶": "3", "エヒ挛毫ˇ": "2"}, "skill": {"骸ìP": "1"}, "decoration": {"0": 0, "1": 0, "2": 0}}, {"type": "得场鲸", "name": "エヒ挛得ヒ]", "caseSkill": "", "defense": ["38", "-1", "-1", "0", "0", "2"], "material": {"エヒ挛喊泶": "3", "エヒ挛毫ˇ": "2"}, "skill": {"骸ìP": "1"}, "decoration": {"0": 1, "1": 0, "2": 0}}, {"type": "得场鲸", "name": "a鹄s@も\", "caseSkill": "", "defense": ["40", "4", "0", "0", "0", "0"], "material": {"a鹄s喊泶": "6", "a鹄s豪Y催": "3"}, "skill": {"菲ǐjて": "1"}, "decoration": {"0": 0, "1": 0, "2": 0}}, {"type": "得场鲸", "name": "a鹄s@も]", "caseSkill": "", "defense": ["40", "4", "0", "0", "0", "0"], "material": {"a鹄s喊泶": "6", "a鹄s豪Y催": "3"}, "skill": {"菲ǐjて": "1"}, "decoration": {"0": 1, "1": 0, "2": 0}}, {"type": "得场鲸", "name": "た[s得ヒ\", "caseSkill": "", "defense": ["40", "-2", "2", "-1", "-1", "1"], "material": {"jた[s氦W澎": "4", "jた[s氦Wブ": "2", "Ws癌": "3", "た[s氦Wブ": "1"}, "skill": {"ボHq": "1"}, "decoration": {"0": 0, "1": 0, "2": 0}}, {"type": "得场鲸", "name": "た[s得ヒ]", "caseSkill": "", "defense": ["40", "-2", "2", "-1", "-1", "1"], "material": {"jた[s氦W澎": "4", "jた[s氦Wブ": "2", "Ws癌": "3", "た[s氦Wブ": "1"}, "skill": {"ボHq": "1"}, "decoration": {"0": 1, "1": 0, "2": 0}}, {"type": "得场鲸", "name": "k尘得ヒ\", "caseSkill": "", "defense": ["40", "0", "-3", "0", "1", "0"], "material": {"k尘氦W澎": "4", "k尘氦Wブ": "2", "Fbホ": "3"}, "skill": {"hBFH": "1"}, "decoration": {"0": 0, "1": 0, "2": 0}}, {"type": "得场鲸", "name": "k尘得ヒ]", "caseSkill": "", "defense": ["40", "0", "-3", "0", "1", "0"], "material": {"k尘氦W澎": "4", "k尘氦Wブ": "2", "Fbホ": "3"}, "skill": {"hBFH": "1"}, "decoration": {"0": 0, "1": 1, "2": 0}}, {"type": "得场鲸", "name": "t尘得ヒ\", "caseSkill": "", "defense": ["40", "0", "0", "-3", "-2", "1"], "material": {"t尘氦Wブ": "4", "t尘喊{饯": "2"}, "skill": {"持@┦": "2", "s办て": "1"}, "decoration": {"0": 0, "1": 0, "2": 0}}, {"type": "得场鲸", "name": "t尘得ヒ]", "caseSkill": "", "defense": ["40", "0", "0", "-3", "-2", "1"], "material": {"t尘氦Wブ": "4", "t尘喊{饯": "2"}, "skill": {"持@┦": "2"}, "decoration": {"0": 1, "1": 0, "2": 0}}, {"type": "得场鲸", "name": "たEs得ヒ\", "caseSkill": "", "defense": ["40", "0", "-3", "2", "0", "1"], "material": {"jたEs氦W澎": "4", "jたEs氦Wブ": "2"}, "skill": {"ボHq": "2"}, "decoration": {"0": 0, "1": 0, "2": 0}}, {"type": "得场鲸", "name": "たEs得ヒ]", "caseSkill": "", "defense": ["40", "0", "-3", "2", "0", "1"], "material": {"jたEs氦W澎": "4", "jたEs氦Wブ": "2"}, "skill": {"ボHq": "1"}, "decoration": {"0": 1, "1": 0, "2": 0}}, {"type": "得场鲸", "name": "rН尘得ヒ\", "caseSkill": "", "defense": ["42", "0", "3", "-3", "0", "1"], "material": {"rН尘氦W澎": "4", "rН尘喊泶": "3", "rrU": "1"}, "skill": {"r@┦": "2", "r妮┦jて": "1"}, "decoration": {"0": 0, "1": 0, "2": 0}}, {"type": "得场鲸", "name": "rН尘得ヒ]", "caseSkill": "", "defense": ["42", "0", "3", "-3", "0", "1"], "material": {"rН尘氦W澎": "4", "rН尘喊泶": "3", "rrU": "1"}, "skill": {"r@┦": "1"}, "decoration": {"0": 2, "1": 0, "2": 0}}, {"type": "得场鲸", "name": "g饫s得ヒ\", "caseSkill": "", "defense": ["42", "-3", "-1", "3", "-1", "0"], "material": {"g饫s喊恁": "4", "g饫s豪Y催": "2", "g饫s喊泶": "3", "sド": "1"}, "skill": {"]": "1"}, "decoration": {"0": 0, "1": 0, "2": 0}}, {"type": "得场鲸", "name": "g饫s得ヒ]", "caseSkill": "", "defense": ["42", "-3", "-1", "3", "-1", "0"], "material": {"g饫s喊恁": "4", "g饫s豪Y催": "2", "g饫s喊泶": "3", "sド": "1"}, "skill": {"]": "1"}, "decoration": {"0": 1, "1": 0, "2": 0}}, {"type": "得场鲸", "name": "ZEs得ヒ\", "caseSkill": "ZEsぇ矮в", "defense": ["44", "3", "-3", "-1", "-1", "0"], "material": {"ZEs氦Wをブ": "4", "ZEs氦j惑癌": "1"}, "skill": {"S懋g阑jて": "1"}, "decoration": {"0": 0, "1": 0, "2": 0}}, {"type": "得场鲸", "name": "ZEs得ヒ]", "caseSkill": "ZEsぇ矮в", "defense": ["44", "3", "-3", "-1", "-1", "0"], "material": {"ZEs氦Wをブ": "4", "ZEs氦j惑癌": "1"}, "skill": {"S懋g阑jて": "1"}, "decoration": {"0": 1, "1": 0, "2": 0}}, {"type": "得场鲸", "name": "d辰s得ヒ\", "caseSkill": "", "defense": ["44", "-1", "2", "-3", "0", "0"], "material": {"d辰s喊泶": "4", "d辰s壕U": "3", "r辰氦j沤": "2"}, "skill": {"裟荸失鹄槐jて": "2", "A莱舫": "1"}, "decoration": {"0": 0, "1": 0, "2": 0}}, {"type": "得场鲸", "name": "d辰s得ヒ]", "caseSkill": "", "defense": ["44", "-1", "2", "-3", "0", "0"], "material": {"d辰s喊泶": "4", "d辰s壕U": "3", "r辰氦j沤": "2"}, "skill": {"裟荸失鹄槐jて": "2"}, "decoration": {"0": 1, "1": 0, "2": 0}}, {"type": "得场鲸", "name": "腹ps得ヒ\", "caseSkill": "", "defense": ["44", "0", "-3", "3", "0", "0"], "material": {"腹ps氦Wをブ": "4", "腹ps氦W澎": "2"}, "skill": {"j磷Z瞒UP": "2"}, "decoration": {"0": 0, "1": 0, "2": 0}}, {"type": "得场鲸", "name": "腹ps得ヒ]", "caseSkill": "", "defense": ["44", "0", "-3", "3", "0", "0"], "material": {"腹ps氦Wをブ": "4", "腹ps氦W澎": "2"}, "skill": {"j磷Z瞒UP": "1"}, "decoration": {"0": 0, "1": 1, "2": 0}}, {"type": "得场鲸", "name": "B爬s得ヒ\", "caseSkill": "", "defense": ["44", "-3", "2", "0", "1", "0"], "material": {"B爬s氦Wをブ": "4", "B爬s氦W澎": "2", "}借w癌": "5"}, "skill": {"コN": "2"}, "decoration": {"0": 0, "1": 0, "2": 0}}, {"type": "得场鲸", "name": "B爬s得ヒ]", "caseSkill": "", "defense": ["44", "-3", "2", "0", "1", "0"], "material": {"B爬s氦Wをブ": "4", "B爬s氦W澎": "2", "}借w癌": "5"}, "skill": {"コN": "1"}, "decoration": {"0": 1, "1": 0, "2": 0}}, {"type": "得场鲸", "name": "慧趵s得ヒ\", "caseSkill": "", "defense": ["46", "2", "0", "-2", "0", "-3"], "material": {"慧趵s喊泶": "4", "慧趵s氦W雌": "2"}, "skill": {"r妮┦jて": "2"}, "decoration": {"0": 0, "1": 0, "2": 0}}, {"type": "得场鲸", "name": "慧趵s得ヒ]", "caseSkill": "", "defense": ["46", "2", "0", "-2", "0", "-3"], "material": {"慧趵s喊泶": "4", "慧趵s氦W雌": "2"}, "skill": {"r妮┦jて": "1"}, "decoration": {"0": 1, "1": 0, "2": 0}}, {"type": "得场鲸", "name": "趵sみ得ヒ\", "caseSkill": "腻趵sぇ而", "defense": ["52", "3", "0", "-3", "0", "-4"], "material": {"腻趵s喊泶": "6", "腻趵s氦W澎": "2", "慧趵s氦W雌": "3", "慧趵s含酯": "1"}, "skill": {"防－@┦": "2"}, "decoration": {"0": 0, "1": 0, "2": 0}}, {"type": "得场鲸", "name": "趵sみ得ヒ]", "caseSkill": "腻趵sぇ而", "defense": ["52", "3", "0", "-3", "0", "-4"], "material": {"腻趵s喊泶": "6", "腻趵s氦W澎": "2", "慧趵s氦W雌": "3", "慧趵s含酯": "1"}, "skill": {"防－@┦": "1"}, "decoration": {"0": 0, "1": 1, "2": 0}}, {"type": "得场鲸", "name": "癌埋s得ヒ\", "caseSkill": "", "defense": ["46", "0", "2", "0", "-1", "-2"], "material": {"癌埋s氦W澎": "4", "癌埋s喊泶": "3", "癌埋s憾陋o催": "2", "w借癌Y": "8"}, "skill": {"何v妮┦jて": "2", "究m┦": "1"}, "decoration": {"0": 0, "1": 0, "2": 0}}, {"type": "得场鲸", "name": "癌埋s得ヒ]", "caseSkill": "", "defense": ["46", "0", "2", "0", "-1", "-2"], "material": {"癌埋s氦W澎": "4", "癌埋s喊泶": "3", "癌埋s憾陋o催": "2", "w借癌Y": "8"}, "skill": {"何v妮┦jて": "1"}, "decoration": {"0": 1, "1": 0, "2": 0}}, {"type": "得场鲸", "name": "━搁s得ヒ\", "caseSkill": "", "defense": ["48", "2", "0", "-3", "0", "2"], "material": {"━搁s氦Wブ": "4", "フ恭ホ": "6"}, "skill": {"导u": "2"}, "decoration": {"0": 0, "1": 0, "2": 0}}, {"type": "得场鲸", "name": "━搁s得ヒ]", "caseSkill": "", "defense": ["48", "2", "0", "-3", "0", "2"], "material": {"━搁s氦Wブ": "4", "フ恭ホ": "6"}, "skill": {"导u": "1"}, "decoration": {"0": 1, "1": 0, "2": 0}}, {"type": "得场鲸", "name": "疟q翰━葵觯\", "caseSkill": "翰ss憾", "defense": ["44", "4", "-3", "-1", "-2", "-3"], "material": {"翰ss杭雠": "3", "翰ss憨ゼ": "2", "谨sホ": "8"}, "skill": {"妮┦秆/杆恶XR": "1"}, "decoration": {"0": 0, "1": 0, "2": 0}}, {"type": "得场鲸", "name": "疟q翰━葵觯]", "caseSkill": "翰ss憾", "defense": ["44", "4", "-3", "-1", "-2", "-3"], "material": {"翰ss杭雠": "3", "翰ss憨ゼ": "2", "谨sホ": "8"}, "skill": {"妮┦秆/杆恶XR": "1"}, "decoration": {"0": 1, "1": 0, "2": 0}}, {"type": "得场鲸", "name": "qホ得ヒ\", "caseSkill": "", "defense": ["50", "0", "-1", "-2", "3", "0"], "material": {"フ恭ホ": "4", "Fbホ": "3"}, "skill": {"究m": "2", "B妮┦ю阑jて": "1"}, "decoration": {"0": 0, "1": 0, "2": 0}}, {"type": "得场鲸", "name": "qホ得ヒ]", "caseSkill": "", "defense": ["50", "0", "-1", "-2", "3", "0"], "material": {"フ恭ホ": "4", "Fbホ": "3"}, "skill": {"究m": "2"}, "decoration": {"0": 1, "1": 0, "2": 0}}, {"type": "得场鲸", "name": "疟K得ヒ\", "caseSkill": "", "defense": ["50", "-2", "0", "3", "-1", "0"], "material": {"フ恭ホ": "1", "绊s癌": "3", "谨sホ": "4", "鹄焕s害yà": "2"}, "skill": {"砰OWj": "2", "p妮┦ю阑jて": "1"}, "decoration": {"0": 0, "1": 0, "2": 0}}, {"type": "得场鲸", "name": "疟K得ヒ]", "caseSkill": "", "defense": ["50", "-2", "0", "3", "-1", "0"], "material": {"フ恭ホ": "1", "绊s癌": "3", "谨sホ": "4", "鹄焕s害yà": "2"}, "skill": {"砰OWj": "2"}, "decoration": {"0": 1, "1": 0, "2": 0}}, {"type": "得场鲸", "name": "裙蔚氓遥\", "caseSkill": "", "defense": ["52", "1", "0", "2", "0", "2"], "material": {"悸yw刽": "2", "g饫sw刽": "4", "趵sw刽": "3"}, "skill": {"ダ护": "2", "弘F[@": "1"}, "decoration": {"0": 0, "1": 0, "2": 0}}, {"type": "得场鲸", "name": "裙蔚氓遥]", "caseSkill": "", "defense": ["52", "1", "0", "2", "0", "2"], "material": {"悸yw刽": "2", "g饫sw刽": "4", "趵sw刽": "3"}, "skill": {"ダ护": "2"}, "decoration": {"0": 1, "1": 0, "2": 0}}, {"type": "得场鲸", "name": "翰━s得ヒ\", "caseSkill": "", "defense": ["56", "3", "-3", "1", "-2", "2"], "material": {"翰━s喊泶": "4", "翰━s氦W澎": "6"}, "skill": {"菲ǐjて": "1"}, "decoration": {"0": 0, "1": 1, "2": 0}}, {"type": "得场鲸", "name": "翰━s得ヒ]", "caseSkill": "", "defense": ["56", "3", "-3", "1", "-2", "2"], "material": {"翰━s喊泶": "4", "翰━s氦W澎": "6"}, "skill": {"菲ǐjて": "1"}, "decoration": {"0": 0, "1": 0, "2": 1}}, {"type": "得场鲸", "name": "泛}s得ヒ\", "caseSkill": "泛}s寒γd", "defense": ["54", "-1", "2", "-3", "3", "0"], "material": {"泛}s氦Wブ": "4", "泛}s骇澜": "3", "A丽舸": "1"}, "skill": {"缚P": "1"}, "decoration": {"0": 0, "1": 0, "2": 0}}, {"type": "得场鲸", "name": "泛}s得ヒ]", "caseSkill": "泛}s寒γd", "defense": ["54", "-1", "2", "-3", "3", "0"], "material": {"泛}s氦Wブ": "4", "泛}s骇澜": "3", "A丽舸": "1"}, "skill": {"缚P": "1"}, "decoration": {"0": 0, "1": 0, "2": 1}}, {"type": "得场鲸", "name": "G隼s得ヒ\", "caseSkill": "G隼s憾", "defense": ["54", "2", "2", "-2", "-3", "0"], "material": {"G隼s氦jw惮": "4", "G隼s骇坤": "2"}, "skill": {"砰N": "1"}, "decoration": {"0": 0, "1": 0, "2": 0}}, {"type": "得场鲸", "name": "G隼s得ヒ]", "caseSkill": "G隼s憾", "defense": ["54", "2", "2", "-2", "-3", "0"], "material": {"G隼s氦jw惮": "4", "G隼s骇坤": "2"}, "skill": {"砰N": "1"}, "decoration": {"0": 1, "1": 0, "2": 0}}, {"type": "得场鲸", "name": "趵s得ヒ\", "caseSkill": "趵s而", "defense": ["54", "3", "1", "-2", "1", "-3"], "material": {"趵s喊泶": "6", "趵sぇl": "2"}, "skill": {"醐@┦": "2", "ю阑": "1"}, "decoration": {"0": 0, "1": 0, "2": 0}}, {"type": "得场鲸", "name": "趵s得ヒ]", "caseSkill": "趵s而", "defense": ["54", "3", "1", "-2", "1", "-3"], "material": {"趵s喊泶": "6", "趵sぇl": "2"}, "skill": {"醐@┦": "2"}, "decoration": {"0": 1, "1": 0, "2": 0}}, {"type": "得场鲸", "name": "趵s活得ヒ\", "caseSkill": "趵s而", "defense": ["56", "3", "2", "2", "-3", "-4"], "material": {"a趵s喊泶": "6", "a趵sぇl": "2", "a趵s骇坤": "1", "荒ls害y": "4"}, "skill": {"栋い": "1"}, "decoration": {"0": 1, "1": 0, "2": 0}}, {"type": "得场鲸", "name": "趵s活得ヒ]", "caseSkill": "趵s而", "defense": ["56", "3", "2", "2", "-3", "-4"], "material": {"a趵s喊泶": "6", "a趵sぇl": "2", "a趵s骇坤": "1", "荒ls害y": "4"}, "skill": {"栋い": "1"}, "decoration": {"0": 0, "1": 1, "2": 0}}, {"type": "得场鲸", "name": "às得ヒ\", "caseSkill": "àsぇ而", "defense": ["54", "3", "-2", "0", "-3", "2"], "material": {"às喊恁": "4", "às喊泶": "6", "às骇昆": "3", "a鹄s喊泶": "5"}, "skill": {"醭酴扦O": "2", "@_": "1"}, "decoration": {"0": 0, "1": 0, "2": 0}}, {"type": "得场鲸", "name": "às得ヒ]", "caseSkill": "àsぇ而", "defense": ["54", "3", "-2", "0", "-3", "2"], "material": {"às喊恁": "4", "às喊泶": "6", "às骇昆": "3", "a鹄s喊泶": "5"}, "skill": {"醭酴扦O": "2"}, "decoration": {"0": 0, "1": 1, "2": 0}}, {"type": "得场鲸", "name": "忌gàs得ヒ\", "caseSkill": "àsぇ而", "defense": ["56", "2", "-3", "0", "-4", "2"], "material": {"堵às喊恁": "4", "堵às喊泶": "6", "Fbホ": "5"}, "skill": {"栋い": "1"}, "decoration": {"0": 0, "1": 0, "2": 0}}, {"type": "得场鲸", "name": "忌gàs得ヒ]", "caseSkill": "àsぇ而", "defense": ["56", "2", "-3", "0", "-4", "2"], "material": {"堵às喊恁": "4", "堵às喊泶": "6", "Fbホ": "5"}, "skill": {"栋い": "1"}, "decoration": {"0": 1, "1": 1, "2": 0}}, {"type": "得场鲸", "name": "z埋s得ヒ\", "caseSkill": "z埋sぇu@", "defense": ["60", "4", "-3", "1", "-2", "-2"], "material": {"z埋s喊泶": "4", "z埋s憨蹬": "1"}, "skill": {"究m┦": "1"}, "decoration": {"0": 1, "1": 0, "2": 0}}, {"type": "得场鲸", "name": "z埋s得ヒ]", "caseSkill": "z埋sぇu@", "defense": ["60", "4", "-3", "1", "-2", "-2"], "material": {"z埋s喊泶": "4", "z埋s憨蹬": "1"}, "skill": {"究m┦": "1"}, "decoration": {"0": 0, "1": 1, "2": 0}}, {"type": "得场鲸", "name": "z澎s得ヒ\", "caseSkill": "z澎sぇu@", "defense": ["58", "3", "1", "-4", "-2", "-2"], "material": {"z澎s喊泶": "4", "z澎s害y": "2", "夯ホ": "1"}, "skill": {"┺MNiмj": "2", "φ峨": "1"}, "decoration": {"0": 0, "1": 0, "2": 0}}, {"type": "得场鲸", "name": "z澎s得ヒ]", "caseSkill": "z澎sぇu@", "defense": ["58", "3", "1", "-4", "-2", "-2"], "material": {"z澎s喊泶": "4", "z澎s害y": "2", "夯ホ": "1"}, "skill": {"┺MNiмj": "2"}, "decoration": {"0": 0, "1": 0, "2": 1}}, {"type": "得场鲸", "name": "j皑h驳氓遥\", "caseSkill": "", "defense": ["60", "4", "-2", "0", "0", "0"], "material": {"jsぇ": "2", "フ恭ホ": "3", "堵às喊恁": "5", "A丽舸": "1"}, "skill": {"K": "1"}, "decoration": {"0": 0, "1": 0, "2": 0}}, {"type": "得场鲸", "name": "j皑h驳氓遥]", "caseSkill": "", "defense": ["60", "4", "-2", "0", "0", "0"], "material": {"jsぇ": "2", "フ恭ホ": "3", "堵às喊恁": "5", "A丽舸": "1"}, "skill": {"K": "1"}, "decoration": {"0": 1, "1": 0, "2": 0}}, {"type": "得场鲸", "name": "猾得ヒ\", "caseSkill": "", "defense": ["60", "-2", "0", "-1", "-1", "4"], "material": {"js癌": "3", "z埋s憨蹬": "1"}, "skill": {"@O娉t^_": "2", "程R郏摸": "1"}, "decoration": {"0": 0, "1": 0, "2": 0}}, {"type": "得场鲸", "name": "猾得ヒ]", "caseSkill": "", "defense": ["60", "-2", "0", "-1", "-1", "4"], "material": {"js癌": "3", "z埋s憨蹬": "1"}, "skill": {"@O娉t^_": "1"}, "decoration": {"0": 2, "1": 0, "2": 0}}, {"type": "得场鲸", "name": "そ|得ヒ\", "caseSkill": "そ|氦蘧", "defense": ["62", "0", "0", "0", "0", "0"], "material": {"阑sw刽": "3", "悸yw刽": "2", "i黏靡G": "1"}, "skill": {"俱称": "1", "舡@┦": "2"}, "decoration": {"0": 1, "1": 0, "2": 0}}, {"type": "得场鲸", "name": "そ|得ヒ]", "caseSkill": "そ|氦蘧", "defense": ["62", "0", "0", "0", "0", "0"], "material": {"阑sw刽": "3", "悸yw刽": "2", "i黏靡G": "1"}, "skill": {"俱称": "1"}, "decoration": {"0": 0, "1": 0, "2": 1}}, {"type": "得场鲸", "name": "函蛮も\", "caseSkill": "", "defense": ["62", "3", "2", "-2", "3", "-4"], "material": {"a鹤ぇガ": "2", "A丽舸": "1"}, "skill": {"栋い": "2", "s妮┦ю阑jて": "1"}, "decoration": {"0": 1, "1": 0, "2": 0}}, {"type": "得场鲸", "name": "函蛮も]", "caseSkill": "", "defense": ["62", "3", "2", "-2", "3", "-4"], "material": {"a鹤ぇガ": "2", "A丽舸": "1"}, "skill": {"栋い": "2"}, "decoration": {"0": 2, "1": 0, "2": 0}}, {"type": "得场鲸", "name": "驹镜氓遥\", "caseSkill": "防荷sぇ哀j", "defense": ["64", "1", "1", "-3", "1", "-3"], "material": {"防荷s喊泶": "4", "防荷s氦jà": "1", "防荷s骇坤": "2"}, "skill": {"D驹": "2", "ю阑": "1"}, "decoration": {"0": 0, "1": 0, "2": 0}}, {"type": "得场鲸", "name": "驹镜氓遥]", "caseSkill": "防荷sぇ哀j", "defense": ["64", "1", "1", "-3", "1", "-3"], "material": {"防荷s喊泶": "4", "防荷s氦jà": "1", "防荷s骇坤": "2"}, "skill": {"D驹": "2"}, "decoration": {"0": 1, "1": 0, "2": 0}}, {"type": "得场鲸", "name": "窑得ヒ\", "caseSkill": "sぇZм", "defense": ["64", "3", "-3", "1", "-3", "1"], "material": {"夯豪s澎": "4"}, "skill": {"zIS": "2"}, "decoration": {"0": 1, "1": 0, "2": 0}}, {"type": "得场鲸", "name": "窑得ヒ]", "caseSkill": "sぇZм", "defense": ["64", "3", "-3", "1", "-3", "1"], "material": {"夯豪s澎": "4"}, "skill": {"zIS": "1"}, "decoration": {"0": 0, "1": 0, "2": 1}}, {"type": "得场鲸", "name": "葵s璞j\", "caseSkill": "葵s涵傅", "defense": ["64", "0", "2", "-3", "4", "-2"], "material": {"葵s喊泶": "5", "葵s害yà": "2", "泛}s喊f澎": "1"}, "skill": {"j磷┦": "2", "K": "1"}, "decoration": {"0": 0, "1": 0, "2": 0}}, {"type": "得场鲸", "name": "葵s璞j]", "caseSkill": "葵s涵傅", "defense": ["64", "0", "2", "-3", "4", "-2"], "material": {"葵s喊泶": "5", "葵s害yà": "2", "泛}s喊f澎": "1"}, "skill": {"j磷┦": "2"}, "decoration": {"0": 0, "1": 0, "2": 1}}, {"type": "得场鲸", "name": "Q棚得ヒ\", "caseSkill": "ほ~寒γd", "defense": ["64", "-3", "-2", "4", "-2", "2"], "material": {"Q棚氦Wブ": "3", "Q棚好Oを": "4", "s叩泊": "6"}, "skill": {"p妮┦ю阑jて": "2", "]": "1"}, "decoration": {"0": 0, "1": 0, "2": 0}}, {"type": "得场鲸", "name": "Q棚得ヒ]", "caseSkill": "ほ~寒γd", "defense": ["64", "-3", "-2", "4", "-2", "2"], "material": {"Q棚氦Wブ": "3", "Q棚好Oを": "4", "s叩泊": "6"}, "skill": {"p妮┦ю阑jて": "2"}, "decoration": {"0": 1, "1": 0, "2": 0}}, {"type": "得场鲸", "name": "Q焊w得ヒ\", "caseSkill": "彤MsぇR", "defense": ["64", "-4", "4", "1", "-1", "-3"], "material": {"彤Ms壕U": "3", "韩酮豪s澎": "6", "彤Ms撼Q饯": "2", "彤Ms耗_ド": "1"}, "skill": {"L端": "1"}, "decoration": {"0": 1, "1": 0, "2": 0}}, {"type": "得场鲸", "name": "Q焊w得ヒ]", "caseSkill": "彤MsぇR", "defense": ["64", "-4", "4", "1", "-1", "-3"], "material": {"彤Ms壕U": "3", "韩酮豪s澎": "6", "彤Ms撼Q饯": "2", "彤Ms耗_ド": "1"}, "skill": {"L端": "1"}, "decoration": {"0": 3, "1": 0, "2": 0}}, {"type": "得场鲸", "name": "钵贺j葵觯\", "caseSkill": "呖Os函", "defense": ["72", "-3", "2", "2", "2", "-4"], "material": {"呖Os亥沾": "4", "呖Os韩栅": "3", "呖Os韩展": "2", "sド": "1"}, "skill": {"搭淮x┠": "1"}, "decoration": {"0": 1, "1": 0, "2": 0}}, {"type": "得场鲸", "name": "钵贺j葵觯]", "caseSkill": "呖Os函", "defense": ["72", "-3", "2", "2", "2", "-4"], "material": {"呖Os亥沾": "4", "呖Os韩栅": "3", "呖Os韩展": "2", "sド": "1"}, "skill": {"搭淮x┠": "1"}, "decoration": {"0": 0, "1": 0, "2": 1}}, {"type": "得场鲸", "name": "(ら)lM痰氓遥\", "caseSkill": "秸d刮氦蘧", "defense": ["70", "2", "2", "2", "2", "2"], "material": {"秸d刮布": "1", "泛}s氦W澎": "8", "a鹤ぇガ": "2"}, "skill": {"{jて": "1"}, "decoration": {"0": 1, "1": 0, "2": 0}}, {"type": "得场鲸", "name": "(ら)lM痰氓遥]", "caseSkill": "秸d刮氦蘧", "defense": ["70", "2", "2", "2", "2", "2"], "material": {"秸d刮布": "1", "泛}s氦W澎": "8", "a鹤ぇガ": "2"}, "skill": {"{jて": "1"}, "decoration": {"0": 0, "1": 1, "2": 0}}]